distantbytes/__init__.py
distantbytes/distantbytes.py
distantbytes-0.0.2.dist-info/LICENSE
distantbytes-0.0.2.dist-info/METADATA
distantbytes-0.0.2.dist-info/WHEEL
distantbytes-0.0.2.dist-info/top_level.txt
distantbytes-0.0.2.dist-info/RECORD
