Metadata-Version: 2.1
Name: distantbytes
Version: 0.0.2
Summary: Print text to a web terminal viewer
Home-page: http://www.distantbytes.com
Author: Thomas Rowntree
Author-email: thomas.james.rowntree@gmail.com
License: UNKNOWN
Platform: UNKNOWN
Classifier: Programming Language :: Python :: 3
Classifier: License :: OSI Approved :: MIT License
Classifier: Operating System :: OS Independent
